{
	"configurations" : 
	[
		{
			"directories" : 
			[
				{
					"build" : ".",
					"jsonFile" : "directory-.-Debug-f5ebdc15457944623624.json",
					"minimumCMakeVersion" : 
					{
						"string" : "3.26"
					},
					"projectIndex" : 0,
					"source" : ".",
					"targetIndexes" : 
					[
						0
					]
				}
			],
			"name" : "Debug",
			"projects" : 
			[
				{
					"directoryIndexes" : 
					[
						0
					],
					"name" : "ft_IRC",
					"targetIndexes" : 
					[
						0
					]
				}
			],
			"targets" : 
			[
				{
					"directoryIndex" : 0,
					"id" : "ft_IRC::@6890427a1f51a3e7e1df",
					"jsonFile" : "target-ft_IRC-Debug-8c570237572327dd727e.json",
					"name" : "ft_IRC",
					"projectIndex" : 0
				}
			]
		}
	],
	"kind" : "codemodel",
	"paths" : 
	{
		"build" : "/Users/loulou/Documents/ft_IRC/cmake-build-debug",
		"source" : "/Users/loulou/Documents/ft_IRC"
	},
	"version" : 
	{
		"major" : 2,
		"minor" : 5
	}
}
